photoprism/Photo.py
photoprism/Session.py
photoprism/__init__.py
photoprism/mimetypes.py
photoprism_client-0.2.1.dist-info/LICENSE
photoprism_client-0.2.1.dist-info/METADATA
photoprism_client-0.2.1.dist-info/WHEEL
photoprism_client-0.2.1.dist-info/top_level.txt
photoprism_client-0.2.1.dist-info/RECORD
