Metadata-Version: 2.1
Name: photoprism-client
Version: 0.2.1
Summary: A Python client to interact with photoprism.
Author-email: mvlnetdev <maartenvanleeuwen1996@gmail.com>
Project-URL: Homepage, https://github.com/mvlnetdev/photoprism_client
Project-URL: Bug Tracker, https://github.com/mvlnetdev/photoprism_client/issues
Project-URL: documentation, https://github.com/mvlnetdev/photoprism_client/blob/main/README.md
Project-URL: changelog, https://github.com/mvlnetdev/photoprism_client/blob/main/changelog.md
Keywords: photoprism,client,api
Classifier: Programming Language :: Python :: 3
Classifier: License :: OSI Approved :: MIT License
Classifier: Operating System :: OS Independent
Requires-Python: >=3.7
License-File: LICENSE
Requires-Dist: requests
